Metadata-Version: 2.1
Name: macrometa-source-snowflake
Version: 1.0.0
Summary: Macrometa Source for extracting data from Snowflake
Home-page: https://github.com/Macrometacorp/macrometa-source-snowflake
Author: Macrometa
Classifier: License :: OSI Approved :: Apache Software License
Classifier: Programming Language :: Python :: 3 :: Only
License-File: LICENSE
Requires-Dist: pipelinewise-singer-python (==1.2.0)
Requires-Dist: snowflake-connector-python[pandas] (==2.7.*)
Requires-Dist: pendulum (==1.2.0)
Requires-Dist: c8connector (>=0.0.24)
Requires-Dist: prometheus-client (==0.16.0)
Provides-Extra: test
Requires-Dist: pylint (==2.12.*) ; extra == 'test'
Requires-Dist: pytest (==7.0.1) ; extra == 'test'
Requires-Dist: pytest-cov (==4.0.0) ; extra == 'test'
Requires-Dist: unify (==0.5) ; extra == 'test'
